<?xml version='1.0' encoding="UTF-8"?>
<!-- $Header: /var/cvsroot/gentoo/xml/htdocs/doc/pl/metadoc.xml,v 1.216 2007/07/04 10:13:07 shadoww Exp $ -->
<!DOCTYPE metadoc SYSTEM "/dtd/metadoc.dtd">

<metadoc lang="pl" parent="/doc/en/metadoc.xml">
<version>1.111</version>
  <members>
    <lead>rane</lead>
    <lead>shadoww</lead>
    <member mail="stawrul@gmail.com" fullname="Waldemar Korłub">stawrul</member>
    <member mail="damjanek@gmail.com" fullname="Damian Szeluga">Damjanek</member>
    <member mail="jbozanowski@gmail.com" fullname="Kuba Bożanowski">iieee</member>
  </members>
  <categories>
    <cat id="faq">Często zadawane pytania</cat>
    <cat id="install">Instalacja Gentoo Linux</cat>
    <cat id="install_guides" parent="install">Opisy instalacji</cat>
    <cat id="install_other"  parent="install">Pozostałe dokumenty</cat>
    <cat id="upgrade">Dokumenty związane z aktualizacją</cat>
    <cat id="articles">Artykuły</cat>
    <cat id="gentoo">Systemowa dokumentacja Gentoo</cat>
    <cat id="gentoo_portage"     parent="gentoo">Dokumentacja dla Portage</cat>
    <cat id="gentoo_configuring" parent="gentoo">Konfiguracja Gentoo</cat>
    <cat id="gentoo_choices"     parent="gentoo">Możliwości Gentoo</cat>
    <cat id="articles_linux"     parent="articles">Nauka Linuksa</cat>
    <cat id="articles_commth"    parent="articles">Artykuły DeveloperWorks Common Threads</cat>
    <cat id="articles_others"    parent="articles">Pozostałe artykuły</cat>
    <cat id="sysadmin">Administrowanie Gentoo</cat>
    <cat id="sysadmin_general"  parent="sysadmin">Ogólna dokumentacja</cat>
    <cat id="sysadmin_specific" parent="sysadmin">Przewodniki dla administratorów</cat>
    <cat id="gentoodev">Dokumentacja związana z rozwijaniem Gentoo</cat>
    <cat id="gentoodev_policies" parent="gentoodev">Zasady rozwijania Gentoo</cat>
    <cat id="gentoodev_docs"     parent="gentoodev">Dokumentacja dla deweloperów</cat>
    <cat id="desktop">Dokumentacja dla Gentoo na stacjach roboczych</cat>
    <cat id="desktop_install" parent="desktop">Instalowanie sterowników i środowisk</cat>
    <cat id="desktop_config"  parent="desktop">Konfigurowanie systemu</cat>
    <cat id="desktop_apps"    parent="desktop">Praca z programami</cat>
    <cat id="other">Pozostałe dokumenty</cat>
    <cat id="project">Dokumentacja poszczególnych projektów</cat>
    <cat id="project_base"    parent="project">Dokumentacja projektu Base</cat>
    <cat id="project_devrel"  parent="project">Dokumentacja Developer Relations</cat>
    <cat id="project_gdp"     parent="project">Dokumentacja Projektu Dokumentacji</cat>
    <cat id="project_hardened" parent="project">Dokumentacja Projektu Hardened</cat>
    <cat id="project_infra"   parent="project">Dokumentacja projektu Infrastructure</cat>
    <cat id="project_metastructure" parent="project">Dokumentacja projektu Metastructure</cat>
    <cat id="project_pr"      parent="project">Dokumentacja projektu Public Relations</cat>
    <cat id="project_releng"  parent="project">Dokumentacja projektu Release Engineering</cat>
    <cat id="project_security" parent="project">Dokumentacja projektu Security</cat>
    <cat id="project_forums"  parent="project">Dokumentacja Forum Gentoo</cat>
  </categories>
  <files>
    <file id="metadoc">/doc/pl/metadoc.xml</file>
    <file id="metadoc-index">/doc/pl/index.xml</file>
    <file id="metadoc-list">/doc/pl/list.xml</file>
    <file id="metadoc-overview">/doc/pl/overview.xml</file>
    <file id="inserts">/doc/pl/inserts.xml</file>
    <file id="name-logo">/main/pl/name-logo.xml</file>
    <file id="art-prompt-magic">/doc/pl/articles/prompt-magic.xml</file>
    <file id="art-bash-ex-p1">/doc/pl/articles/bash-by-example-p1.xml</file>
    <file id="art-bash-ex-p2">/doc/pl/articles/bash-by-example-p2.xml</file>
    <file id="art-bash-ex-p3">/doc/pl/articles/bash-by-example-p3.xml</file>
    <file id="art-mk-distro-p1">/doc/en/articles/making-the-distro-p1.xml</file>
    <file id="art-mk-distro-p2">/doc/en/articles/making-the-distro-p2.xml</file>
    <file id="art-mk-distro-p3">/doc/en/articles/making-the-distro-p3.xml</file>
    <file id="art-lpi-101-fundamentals-p1">/doc/pl/articles/lpi-101-fundamentals-p1.xml</file>
    <file id="art-lpi-101-administration-p2">/doc/pl/articles/lpi-101-administration-p2.xml</file>
    <file id="art-lpi-101-intermediate-p3">/doc/en/articles/lpi-101-intermediate-p3.xml</file>
    <file id="art-lpi-101-advanced-p4">/doc/en/articles/lpi-101-advanced-p4.xml</file>
    <file id="art-ct-dyn-iptables-fw">/doc/pl/articles/dynamic-iptables-firewalls.xml</file>
    <file id="art-ct-l-sed-p1">/doc/pl/articles/l-sed1.xml</file>
    <file id="art-ct-l-sed-p2">/doc/pl/articles/l-sed2.xml</file>
    <file id="art-ct-l-sed-p3">/doc/pl/articles/l-sed3.xml</file>
    <file id="art-ct-l-awk-p1">/doc/pl/articles/l-awk1.xml</file>
    <file id="art-ct-l-awk-p2">/doc/pl/articles/l-awk2.xml</file>
    <file id="art-ct-l-awk-p3">/doc/pl/articles/l-awk3.xml</file>
    <file id="art-ct-l-posix-p1">/doc/pl/articles/l-posix1.xml</file>
    <file id="art-ct-l-posix-p2">/doc/pl/articles/l-posix2.xml</file>
    <file id="art-ct-l-posix-p3">/doc/pl/articles/l-posix3.xml</file>
    <file id="art-ct-sta-iptables-fw">/doc/pl/articles/linux-24-stateful-fw-design.xml</file>
    <file id="afig-ct-ext3-intro">/doc/en/articles/afig-ct-ext3-intro.xml</file>
    <file id="hardware-stability-p1">/doc/en/articles/hardware-stability-p1.xml</file>
    <file id="hardware-stability-p2">/doc/en/articles/hardware-stability-p2.xml</file>
    <file id="partitioning-p1">/doc/pl/articles/partitioning-p1.xml</file>
    <file id="partitioning-p2">/doc/pl/articles/partitioning-p2.xml</file>
    <file id="partition-planning-tips">/doc/pl/articles/partition-planning-tips.xml</file>
    <file id="maximum-swappage">/doc/pl/articles/maximum-swappage.xml</file>
    <file id="lvm-p1">/doc/en/articles/lvm-p1.xml</file>
    <file id="lvm-p2">/doc/en/articles/lvm-p2.xml</file>
    <file id="software-raid-p1">/doc/en/articles/software-raid-p1.xml</file>
    <file id="software-raid-p2">/doc/en/articles/software-raid-p2.xml</file>
    <file id="linux-kernel-compiling">/doc/en/articles/linux-kernel-compiling.xml</file>
    <file id="openssh-key-management-p1">/doc/pl/articles/openssh-key-management-p1.xml</file>
    <file id="openssh-key-management-p2">/doc/pl/articles/openssh-key-management-p2.xml</file>
    <file id="openssh-key-management-p3">/doc/pl/articles/openssh-key-management-p3.xml</file>
    <file id="l-afig-p8">/doc/en/articles/l-afig-p8.xml</file>
    <file id="samba-p1">/doc/pl/articles/samba-p1.xml</file>
    <file id="samba-p2">/doc/pl/articles/samba-p2.xml</file>
    <file id="samba-p3">/doc/pl/articles/samba-p3.xml</file>
    <file id="l-redesign-1">/doc/en/articles/l-redesign-1.xml</file>
    <file id="l-redesign-2">/doc/en/articles/l-redesign-2.xml</file>
    <file id="l-redesign-3">/doc/en/articles/l-redesign-3.xml</file>
    <file id="l-redesign-4">/doc/en/articles/l-redesign-4.xml</file>
    <file id="autotools-practices">/doc/en/articles/autotools-practices.xml</file>
    <file id="bugzie-howto">/doc/pl/bugzilla-howto.xml</file>
    <file id="mysql-howto">/doc/pl/mysql-howto.xml</file>
    <file id="postgres-howto">/doc/pl/postgres-howto.xml</file>
    <file id="bt-guide">/doc/pl/bluetooth-guide.xml</file>
    <file id="utf-8">/doc/pl/utf-8.xml</file>
    <file id="cron-guide">/doc/pl/cron-guide.xml</file>
    <file id="ldap-howto">/doc/pl/ldap-howto.xml</file>
    <file id="nvidia-guide">/doc/pl/nvidia-guide.xml</file>
    <file id="ati-faq">/doc/pl/ati-faq.xml</file>
    <file id="cvs-tutorial">/doc/pl/cvs-tutorial.xml</file>
    <file id="devfs-guide">/doc/pl/devfs-guide.xml</file>
    <file id="distcc">/doc/pl/distcc.xml</file>
    <file id="cross-distcc">/doc/pl/cross-compiling-distcc.xml</file>
    <file id="dri-howto">/doc/pl/dri-howto.xml</file>
    <file id="ebuild-submit">/doc/pl/ebuild-submit.xml</file>
    <file id="gentoo-upgrading">/doc/pl/gentoo-upgrading.xml</file>
    <file id="2.6-migration">/doc/pl/migration-to-2.6.xml</file>
    <file id="altinstall">/doc/pl/altinstall.xml</file>
    <file id="faq">/doc/pl/faq.xml</file>
    <file id="gentoo-alpha-faq">/doc/pl/gentoo-alpha-faq.xml</file>
    <file id="gentoo-amd64-faq">/doc/pl/gentoo-amd64-faq.xml</file>
    <file id="handbook-alpha">/doc/pl/handbook/handbook-alpha.xml</file>
    <file id="handbook-amd64">/doc/pl/handbook/handbook-amd64.xml</file>
    <file id="handbook-arm">/doc/en/handbook/handbook-arm.xml</file>
    <file id="handbook-hppa">/doc/pl/handbook/handbook-hppa.xml</file>
    <file id="handbook-ia64">/doc/pl/handbook/handbook-ia64.xml</file>
    <file id="handbook-mips">/doc/pl/handbook/handbook-mips.xml</file>
    <file id="handbook-ppc">/doc/pl/handbook/handbook-ppc.xml</file>
    <file id="handbook-ppc64">/doc/pl/handbook/handbook-ppc64.xml</file>
    <file id="handbook-sparc">/doc/pl/handbook/handbook-sparc.xml</file>
    <file id="handbook-x86">/doc/pl/handbook/handbook-x86.xml</file>
    <file id="hb-portage-branches">/doc/pl/handbook/hb-portage-branches.xml</file>
    <file id="hb-install-about">/doc/pl/handbook/hb-install-about.xml</file>
    <file id="hb-install-alpha-bootloader">/doc/pl/handbook/hb-install-alpha-bootloader.xml</file>
    <file id="2007.0-handbook-amd64">/doc/pl/handbook/2007.0/handbook-amd64.xml</file>
    <file id="2007.0-handbook-hppa">/doc/pl/handbook/2007.0/handbook-hppa.xml</file>
    <file id="2007.0-handbook-ppc64">/doc/pl/handbook/2007.0/handbook-ppc64.xml</file>
    <file id="2007.0-handbook-ppc">/doc/pl/handbook/2007.0/handbook-ppc.xml</file>
    <file id="2007.0-handbook-sparc">/doc/pl/handbook/2007.0/handbook-sparc.xml</file>
    <file id="2007.0-handbook-x86">/doc/pl/handbook/2007.0/handbook-x86.xml</file>
    <file id="2007.0-hb-install-about">/doc/pl/handbook/2007.0/hb-install-about.xml</file>
    <file id="2007.0-hb-install-config">/doc/pl/handbook/2007.0/hb-install-config.xml</file>
    <file id="2007.0-hb-install-finalise">/doc/pl/handbook/2007.0/hb-install-finalise.xml</file>
    <file id="2007.0-hb-install-hppa-bootloader">/doc/pl/handbook/2007.0/hb-install-hppa-bootloader.xml</file>
    <file id="2007.0-hb-install-hppa-disk">/doc/pl/handbook/2007.0/hb-install-hppa-disk.xml</file>
    <file id="2007.0-hb-install-hppa-kernel">/doc/pl/handbook/2007.0/hb-install-hppa-kernel.xml</file>
    <file id="2007.0-hb-install-hppa-medium">/doc/pl/handbook/2007.0/hb-install-hppa-medium.xml</file>
    <file id="2007.0-hb-install-network">/doc/pl/handbook/2007.0/hb-install-network.xml</file>
    <file id="2007.0-hb-install-next">/doc/pl/handbook/2007.0/hb-install-next.xml</file>
    <file id="2007.0-hb-install-ppc64-bootloader">/doc/pl/handbook/2007.0/hb-install-ppc64-bootloader.xml</file>
    <file id="2007.0-hb-install-ppc64-disk">/doc/pl/handbook/2007.0/hb-install-ppc64-disk.xml</file>
    <file id="2007.0-hb-install-ppc64-kernel">/doc/pl/handbook/2007.0/hb-install-ppc64-kernel.xml</file>
    <file id="2007.0-hb-install-ppc64-medium">/doc/pl/handbook/2007.0/hb-install-ppc64-medium.xml</file>
    <file id="2007.0-hb-install-ppc-bootloader">/doc/pl/handbook/2007.0/hb-install-ppc-bootloader.xml</file>
    <file id="2007.0-hb-install-ppc-disk">/doc/pl/handbook/2007.0/hb-install-ppc-disk.xml</file>
    <file id="2007.0-hb-install-ppc-kernel">/doc/pl/handbook/2007.0/hb-install-ppc-kernel.xml</file>
    <file id="2007.0-hb-install-ppc-medium">/doc/pl/handbook/2007.0/hb-install-ppc-medium.xml</file>
    <file id="2007.0-hb-install-sparc-bootloader">/doc/pl/handbook/2007.0/hb-install-sparc-bootloader.xml</file>
    <file id="2007.0-hb-install-sparc-disk">/doc/pl/handbook/2007.0/hb-install-sparc-disk.xml</file>
    <file id="2007.0-hb-install-sparc-kernel">/doc/pl/handbook/2007.0/hb-install-sparc-kernel.xml</file>
    <file id="2007.0-hb-install-sparc-medium">/doc/pl/handbook/2007.0/hb-install-sparc-medium.xml</file>
    <file id="2007.0-hb-install-stage">/doc/pl/handbook/2007.0/hb-install-stage.xml</file>
    <file id="2007.0-hb-install-system">/doc/pl/handbook/2007.0/hb-install-system.xml</file>
    <file id="2007.0-hb-install-tools">/doc/pl/handbook/2007.0/hb-install-tools.xml</file>
    <file id="2007.0-hb-install-gli-dialog">/doc/pl/handbook/2007.0/hb-install-gli-dialog.xml</file>
    <file id="2007.0-hb-install-gli-medium">/doc/pl/handbook/2007.0/hb-install-gli-medium.xml</file>
    <file id="2007.0-hb-install-gtkfe">/doc/pl/handbook/2007.0/hb-install-gtkfe.xml</file>
    <file id="2007.0-index">/doc/pl/handbook/2007.0/index.xml</file>
    <file id="hb-install-alpha-disk">/doc/pl/handbook/hb-install-alpha-disk.xml</file>
    <file id="hb-install-alpha-kernel">/doc/pl/handbook/hb-install-alpha-kernel.xml</file>
    <file id="hb-install-alpha-medium">/doc/pl/handbook/hb-install-alpha-medium.xml</file>
    <file id="hb-install-arm-bootloader">/doc/en/handbook/hb-install-arm-bootloader.xml</file>
    <file id="hb-install-arm-disk">/doc/en/handbook/hb-install-arm-disk.xml</file>
    <file id="hb-install-arm-kernel">/doc/en/handbook/hb-install-arm-kernel.xml</file>
    <file id="hb-install-arm-medium">/doc/en/handbook/hb-install-arm-medium.xml</file>
    <file id="hb-install-config">/doc/pl/handbook/hb-install-config.xml</file>
    <file id="hb-install-finalise">/doc/pl/handbook/hb-install-finalise.xml</file>
    <file id="hb-install-hppa-bootloader">/doc/pl/handbook/hb-install-hppa-bootloader.xml</file>
    <file id="hb-install-hppa-disk">/doc/pl/handbook/hb-install-hppa-disk.xml</file>
    <file id="hb-install-hppa-kernel">/doc/pl/handbook/hb-install-hppa-kernel.xml</file>
    <file id="hb-install-hppa-medium">/doc/pl/handbook/hb-install-hppa-medium.xml</file>
    <file id="hb-install-ia64-disk">/doc/pl/handbook/hb-install-ia64-disk.xml</file>
    <file id="hb-install-ia64-kernel">/doc/pl/handbook/hb-install-ia64-kernel.xml</file>
    <file id="hb-install-ia64-medium">/doc/pl/handbook/hb-install-ia64-medium.xml</file>
    <file id="hb-install-mips-bootloader">/doc/pl/handbook/hb-install-mips-bootloader.xml</file>
    <file id="hb-install-mips-disk">/doc/pl/handbook/hb-install-mips-disk.xml</file>
    <file id="hb-install-mips-kernel">/doc/pl/handbook/hb-install-mips-kernel.xml</file>
    <file id="hb-install-mips-medium">/doc/pl/handbook/hb-install-mips-medium.xml</file>
    <file id="hb-install-mips-stage">/doc/pl/handbook/hb-install-mips-stage.xml</file>
    <file id="hb-install-mips-system.xml">/doc/pl/handbook/hb-install-mips-system.xml</file>
    <file id="hb-install-network">/doc/pl/handbook/hb-install-network.xml</file>
    <file id="hb-install-next">/doc/pl/handbook/hb-install-next.xml</file>
    <file id="hb-install-ppc-bootloader">/doc/pl/handbook/hb-install-ppc-bootloader.xml</file>
    <file id="hb-install-ppc-disk">/doc/pl/handbook/hb-install-ppc-disk.xml</file>
    <file id="hb-install-ppc-kernel">/doc/pl/handbook/hb-install-ppc-kernel.xml</file>
    <file id="hb-install-ppc-medium">/doc/pl/handbook/hb-install-ppc-medium.xml</file>
    <file id="hb-install-ppc64-bootloader">/doc/pl/handbook/hb-install-ppc64-bootloader.xml</file>
    <file id="hb-install-ppc64-disk">/doc/pl/handbook/hb-install-ppc64-disk.xml</file>
    <file id="hb-install-ppc64-kernel">/doc/pl/handbook/hb-install-ppc64-kernel.xml</file>
    <file id="hb-install-ppc64-medium">/doc/pl/handbook/hb-install-ppc64-medium.xml</file>
    <file id="hb-install-sparc-bootloader">/doc/pl/handbook/hb-install-sparc-bootloader.xml</file>
    <file id="hb-install-sparc-disk">/doc/pl/handbook/hb-install-sparc-disk.xml</file>
    <file id="hb-install-sparc-kernel">/doc/pl/handbook/hb-install-sparc-kernel.xml</file>
    <file id="hb-install-sparc-medium">/doc/pl/handbook/hb-install-sparc-medium.xml</file>
    <file id="hb-install-stage">/doc/pl/handbook/hb-install-stage.xml</file>
    <file id="hb-install-tools">/doc/pl/handbook/hb-install-tools.xml</file>
    <file id="hb-install-amd64-bootloader">/doc/pl/handbook/hb-install-x86+amd64-bootloader.xml</file>
    <file id="hb-install-x86-disk">/doc/pl/handbook/hb-install-x86+amd64-disk.xml</file>
    <file id="hb-install-x86-kernel">/doc/pl/handbook/hb-install-x86+amd64-kernel.xml</file>
    <file id="hb-install-x86-medium">/doc/pl/handbook/hb-install-x86+amd64-medium.xml</file>
    <file id="hb-working-features">/doc/pl/handbook/hb-working-features.xml</file>
    <file id="hb-working-portage">/doc/pl/handbook/hb-working-portage.xml</file>
    <file id="hb-working-rcscripts">/doc/pl/handbook/hb-working-rcscripts.xml</file>
    <file id="hb-working-use">/doc/pl/handbook/hb-working-use.xml</file>
    <file id="hb-working-variables">/doc/pl/handbook/hb-working-variables.xml</file>
    <file id="handbook_index">/doc/pl/handbook/index.xml</file>
    <file id="hb-install-system">/doc/pl/handbook/hb-install-system.xml</file>
    <file id="hb-portage-configuration">/doc/pl/handbook/hb-portage-configuration.xml</file>
    <file id="hb-portage-diverttree">/doc/pl/handbook/hb-portage-diverttree.xml</file>
    <file id="hb-portage-files">/doc/pl/handbook/hb-portage-files.xml</file>
    <file id="hb-portage-tools">/doc/pl/handbook/hb-portage-tools.xml</file>
    <file id="hb-net-advanced">/doc/pl/handbook/hb-net-advanced.xml</file>
    <file id="hb-net-functions">/doc/pl/handbook/hb-net-functions.xml</file>
    <file id="hb-net-management">/doc/pl/handbook/hb-net-management.xml</file>
    <file id="hb-net-modules">/doc/pl/handbook/hb-net-modules.xml</file>
    <file id="hb-net-start">/doc/pl/handbook/hb-net-start.xml</file>
    <file id="hb-net-wireless">/doc/pl/handbook/hb-net-wireless.xml</file>
    <file id="lvm2">/doc/pl/lvm2.xml</file>
    <file id="gentoo-kernel">/doc/pl/gentoo-kernel.xml</file>
    <file id="gentoo-ppc-faq">/doc/pl/gentoo-ppc-faq.xml</file>
    <file id="alsa-guide">/doc/pl/alsa-guide.xml</file>
    <file id="xorg-config">/doc/pl/xorg-config.xml</file>
    <file id="quick-samba-howto">/doc/pl/quick-samba-howto.xml</file>
    <file id="ltsp">/doc/pl/ltsp.xml</file>
    <file id="gentoolkit">/doc/pl/gentoolkit.xml</file>
    <file id="gentoo-sparc-quickinstall">/doc/pl/gentoo-sparc-quickinstall.xml</file>
    <file id="gnupg-user">/doc/pl/gnupg-user.xml</file>
    <file id="ipv6">/doc/pl/ipv6.xml</file>
    <file id="guide-localization">/doc/pl/guide-localization.xml</file>
    <file id="guide-to-mutt">/doc/pl/guide-to-mutt.xml</file>
    <file id="uml">/doc/pl/uml.xml</file>
    <file id="java">/doc/pl/java.xml</file>
    <file id="openafs">/doc/pl/openafs.xml</file>
    <file id="kde-config">/doc/pl/kde-config.xml</file>
    <file id="nano-basics-guide">/doc/pl/nano-basics-guide.xml</file>
    <file id="shoutcast-config">/doc/pl/shoutcast-config.xml</file>
    <file id="vdr-guide">/doc/en/vdr-guide.xml</file>
    <file id="xml-guide">/doc/pl/xml-guide.xml</file>
    <file id="diskless-howto">/doc/pl/diskless-howto.xml</file>
    <file id="prelink-howto">/doc/pl/prelink-howto.xml</file>
    <file id="printing-howto">/doc/pl/printing-howto.xml</file>
    <file id="rsync">/doc/pl/rsync.xml</file>
    <file id="qmail-howto">/doc/pl/qmail-howto.xml</file>
    <file id="source_mirrors">/doc/pl/source_mirrors.xml</file>
    <file id="gentoo-ppc-install">/doc/pl/gentoo-ppc-install.xml</file>
    <file id="gentoo-x86-quickinstall">/doc/pl/gentoo-x86-quickinstall.xml</file>
    <file id="gentoo-x86-quickinstall+raid">/doc/pl/gentoo-x86+raid+lvm2-quickinstall.xml</file>
    <file id="vi-guide">/doc/pl/vi-guide.xml</file>
    <file id="virt-mail-howto">/doc/pl/virt-mail-howto.xml</file>
    <file id="mailfilter-guide">/doc/pl/mailfilter-guide.xml</file>
    <file id="genkernel">/doc/pl/genkernel.xml</file>
    <file id="gentoo-sparc-faq">/doc/pl/gentoo-sparc-faq.xml</file>
    <file id="gentoo-x86-install">/doc/pl/gentoo-x86-install.xml</file>
    <file id="mips-requirements">/doc/pl/mips-requirements.xml</file>
    <file id="gentoo-sparc-install">/doc/en/gentoo-sparc-install.xml</file>
    <file id="gentoo-hppa-install">/doc/en/gentoo-hppa-install.xml</file>
    <file id="gentoo-alpha-install">/doc/en/gentoo-alpha-install.xml</file>
    <file id="gentoo-mips-install">/doc/en/gentoo-mips-install.xml</file>
    <file id="udev-guide">/doc/pl/udev-guide.xml</file>
    <file id="gentoo-x86-tipsntricks">/doc/pl/gentoo-x86-tipsntricks.xml</file>
    <file id="gentoo-sparc-netboot-howto">/doc/pl/gentoo-sparc-netboot-howto.xml</file>
    <file id="gentoo-sparc-obpreference">/doc/pl/gentoo-sparc-obpreference.xml</file>
    <file id="gnome-config">/doc/pl/gnome-config.xml</file>
    <file id="gnome-upgrade">/proj/pl/desktop/gnome/howtos/gnome-2.16-upgrade.xml</file>
    <file id="gpm">/doc/pl/gpm.xml</file>
    <file id="gentoo-security">/doc/pl/gentoo-security.xml</file>
    <file id="home-router-howto">/doc/pl/home-router-howto.xml</file>
    <file id="arm-requirements">/doc/en/arm-requirements.xml</file>
    <file id="power-management-guide">/doc/pl/power-management-guide.xml</file>
    <file id="new-upgrade-to-gentoo-1.4">/doc/pl/new-upgrade-to-gentoo-1.4.xml</file>
    <file id="portage-utils">/doc/pl/portage-utils.xml</file>
    <file id="amd64-howtos">/proj/pl/base/amd64/howtos/index.xml</file>
    <file id="amd64-howtos-bugs">/proj/pl/base/amd64/howtos/bugs.xml</file>
    <file id="amd64-howtos-chroot">/proj/pl/base/amd64/howtos/chroot-old.xml</file>
    <file id="amd64-howtos-fpic">/proj/en/base/amd64/howtos/fpic-howto.xml</file>
    <file id="gentoo-dev-handbook">/proj/pl/devrel/handbook/handbook.xml</file>
    <file id="doc-policy">/proj/en/gdp/doc/doc-policy.xml</file>
    <file id="doc-tipsntricks">/proj/pl/gdp/doc/doc-tipsntricks.xml</file>
    <file id="about">/main/pl/about.xml</file>
    <file id="philosophy">/main/pl/philosophy.xml</file>
    <file id="contract">/main/pl/contract.xml</file>
    <file id="contact">/main/pl/contact.xml</file>
    <file id="gentoo-graphics">/main/pl/graphics.xml</file>
    <file id="irc">/main/pl/irc.xml</file>
    <file id="mailing-lists">/main/pl/lists.xml</file>
    <file id="screenshots">/main/pl/shots.xml</file>
    <file id="sponsors">/main/pl/sponsors.xml</file>
    <file id="howto-obtain-support">/main/pl/support.xml</file>
    <file id="where-to-get">/main/pl/where.xml</file>
    <file id="site">/proj/pl/site.xml</file>
    <file id="kernel-upgrade">/doc/pl/kernel-upgrade.xml</file>
    <file id="modular-x-howto">/proj/pl/desktop/x/x11/modular-x-howto.xml</file>
    <file id="porting-modular-x">/proj/pl/desktop/x/x11/porting-modular-x-howto.xml</file>
    <file id="new-dev-training">/proj/en/devrel/new-dev-training.xml</file>
    <file id="devrel-policy">/proj/en/devrel/policy.xml</file>
    <file id="translators-howto">/proj/en/gdp/doc/translators-howto.xml</file>
    <file id="hardened-primer">/proj/pl/hardened/primer.xml</file>
    <file id="hardened-faq">/proj/pl/hardened/hardenedfaq.xml</file>
    <file id="hardened-xorg">/proj/pl/hardened/hardenedxorg.xml</file>
    <file id="hardened-pax-quickstart">/proj/pl/hardened/pax-quickstart.xml</file>
    <file id="hardened-grsec">/proj/en/hardened/grsecurity.xml</file>
    <file id="hardened-capabilities">/proj/pl/hardened/capabilities.xml</file>
    <file id="hardened-selinux">/proj/pl/hardened/selinux/selinux-handbook.xml</file>
    <file id="hardened-rsbac-overview">/proj/pl/hardened/rsbac/overview.xml</file>
    <file id="hardened-rsbac-quickstart">/proj/pl/hardened/rsbac/quickstart.xml</file>
    <file id="infra-email">/proj/en/infrastructure/dev-email.xml</file>
    <file id="infra-cvsssh">/proj/en/infrastructure/cvs-sshkeys.xml</file>
    <file id="infra-machines">/proj/en/infrastructure/dev-machines.xml</file>
    <file id="infra-servers">/proj/en/infrastructure/server-specs.xml</file>
    <file id="infra-serverstandards">/proj/en/infrastructure/server-standards.xml</file>
    <file id="infra-tenshi">/proj/pl/infrastructure/tenshi/index.xml</file>
    <file id="infra-ntp">/proj/en/infrastructure/config-ntp.xml</file>
    <file id="infra-ssh">/proj/en/infrastructure/config-ssh.xml</file>
    <file id="infra-syslog">/proj/en/infrastructure/config-syslog.xml</file>
    <file id="infra-webspace">/proj/en/infrastructure/dev-webspace.xml</file>
    <file id="infra-faq">/proj/en/infrastructure/faq.xml</file>
    <file id="infra-rsync">/proj/en/infrastructure/mirrors-rsync.xml</file>
    <file id="metastructure-projectxml">/proj/en/metastructure/projectxml.xml</file>
    <file id="pr-presentation">/proj/en/pr/docs/howto-presentation.xml</file>
    <file id="catalyst-faq">/proj/pl/releng/catalyst/faq.xml</file>
    <file id="installer-design">/proj/pl/releng/installer/design.xml</file>
    <file id="releng-guidelines">/proj/en/releng/docs/release_guidelines.xml</file>
    <file id="profile-update">/proj/en/releng/release/2004.0/releng/profile-update.xml</file>
    <file id="forums-guide">/proj/en/forums/forum-guide.xml</file>
    <file id="security-index">/security/en/index.xml</file>
    <file id="security-policy">/security/pl/vulnerability-policy.xml</file>
    <file id="security-coordination">/security/en/coordinator_guide.xml</file>
    <file id="security-recruitment">/security/en/padawans.xml</file>
    <file id="security-bugs">/security/en/bug-searching.xml</file>
    <file id="keychain-guide">/doc/pl/keychain-guide.xml</file>
    <file id="metadoc-guide">/proj/en/gdp/doc/metadoc-guide.xml</file>
    <file id="hpc-howto">/doc/pl/hpc-howto.xml</file>
    <file id="gnap-userguide">/proj/en/base/embedded/gnap-userguide.xml</file>
    <file id="kde-split-ebuilds">/doc/pl/kde-split-ebuilds.xml</file>
    <file id="grub-error-guide">/doc/pl/grub-error-guide.xml</file>
    <file id="usb-guide">/doc/pl/usb-guide.xml</file>
    <file id="liveusb">/doc/pl/liveusb.xml</file>
    <file id="fluxbox-config">/doc/pl/fluxbox-config.xml</file>
    <file id="vserver-howto">/proj/en/vps/vserver-howto.xml</file>
    <file id="security-handbook-index">/doc/pl/security/index.xml</file>
    <file id="security-handbook">/doc/pl/security/security-handbook.xml</file>
    <file id="shb-chroot">/doc/pl/security/shb-chroot.xml</file>
    <file id="shb-firewalls">/doc/pl/security/shb-firewalls.xml</file>
    <file id="shb-intrusion">/doc/pl/security/shb-intrusion.xml</file>
    <file id="shb-kernel">/doc/pl/security/shb-kernel.xml</file>
    <file id="shb-limits">/doc/pl/security/shb-limits.xml</file>
    <file id="shb-logging">/doc/pl/security/shb-logging.xml</file>
    <file id="shb-mounting">/doc/pl/security/shb-mounting.xml</file>
    <file id="shb-pam">/doc/pl/security/shb-pam.xml</file>
    <file id="shb-perms">/doc/pl/security/shb-perms.xml</file>
    <file id="shb-pre">/doc/pl/security/shb-pre.xml</file>
    <file id="shb-tcp">/doc/pl/security/shb-tcp.xml</file>
    <file id="shb-services">/doc/pl/security/shb-services.xml</file>
    <file id="shb-tight">/doc/pl/security/shb-tight.xml</file>
    <file id="shb-uptodate">/doc/pl/security/shb-uptodate.xml</file>
    <file id="apache-troubleshooting">/doc/pl/apache-troubleshooting.xml</file>
    <file id="apache-upgrading">/doc/pl/apache-upgrading.xml</file>
    <file id="mysql-upgrade-slotted">/doc/pl/mysql-upgrade-slotted.xml</file>
    <file id="apache-developer">/doc/en/apache-developer.xml</file>
    <file id="sudo-guide">/doc/pl/sudo-guide.xml</file>
    <file id="freebsd-guide">/doc/pl/gentoo-freebsd.xml</file>
    <file id="mips-faq">/doc/pl/gentoo-mips-faq.xml</file>
    <file id="mysql-upgrading">/doc/pl/mysql-upgrading.xml</file>
    <file id="gcc-upgrading">/doc/pl/gcc-upgrading.xml</file>
    <file id="x86-at-faq">/proj/en/base/x86/arch-testers-faq.xml</file>
    <file id="php-upgrade">/proj/pl/php/php-upgrading.xml</file>
    <file id="jffnms">/doc/pl/jffnms.xml</file>
    <file id="conky">/doc/pl/conky-howto.xml</file>
    <file id="ldapdns">/doc/pl/ldapdns-guide.xml</file>
    <file id="man-guide">/doc/pl/man-guide.xml</file>
    <file id="info-guide">/doc/pl/info-guide.xml</file>
    <file id="java-upgrade">/proj/pl/java/java-upgrade.xml</file>
    <file id="kernel-config">/doc/pl/kernel-config.xml</file>
    <file id="zsh">/doc/pl/zsh.xml</file>
    <file id="change-chost">/doc/pl/change-chost.xml</file>
    <file id="xfce-config">/doc/pl/xfce-config.xml</file>
    <file id="gcc-optimization">/doc/pl/gcc-optimization.xml</file>
    <file id="vpnc-howto">/doc/en/vpnc-howto.xml</file>
    <file id="qa-autofailure">/proj/en/qa/autofailure.xml</file>
    <file id="qa-automagic">/proj/en/qa/automagic.xml</file>
    <file id="qa-backtraces">/proj/pl/qa/backtraces.xml</file>
    <file id="manually-fixing-portage">/proj/pl/portage/doc/manually-fixing-portage.xml</file>
  </files>
  <docs>
    <doc id="name-logo">
      <memberof>other</memberof>
      <fileid>name-logo</fileid>
    </doc>
    <doc id="art-bash-ex-p1">
      <memberof>articles_linux</memberof>
      <fileid>art-bash-ex-p1</fileid>
    </doc>
    <doc id="art-bash-ex-p2">
      <memberof>articles_linux</memberof>
      <fileid>art-bash-ex-p2</fileid>
    </doc>
    <doc id="art-bash-ex-p3">
      <memberof>articles_linux</memberof>
      <fileid>art-bash-ex-p3</fileid>
    </doc>
    <doc id="art-mk-distro-p1">
      <memberof>articles_gentoo</memberof>
      <fileid>art-mk-distro-p1</fileid>
    </doc>
    <doc id="art-mk-distro-p2">
      <memberof>articles_gentoo</memberof>
      <fileid>art-mk-distro-p2</fileid>
    </doc>
    <doc id="art-mk-distro-p3">
      <memberof>articles_gentoo</memberof>
      <fileid>art-mk-distro-p3</fileid>
    </doc>
    <doc id="art-lpi-101-fundamentals-p1">
      <memberof>articles_linux</memberof>
      <fileid>art-lpi-101-fundamentals-p1</fileid>
    </doc>
    <doc id="art-lpi-101-administration-p2">
       <memberof>articles_linux</memberof>
       <fileid>art-lpi-101-administration-p2</fileid>
    </doc>
    <doc id="art-lpi-101-intermediate-p3">
      <memberof>articles_linux</memberof>
      <fileid>art-lpi-101-intermediate-p3</fileid>
    </doc>
    <doc id="art-lpi-101-advanced-p4">
      <memberof>articles_linux</memberof>
      <fileid>art-lpi-101-advanced-p4</fileid>
    </doc>
    <doc id="art-ct-dyn-iptables-fw">
      <memberof>articles_commth</memberof>
      <fileid>art-ct-dyn-iptables-fw</fileid>
    </doc>
    <doc id="art-ct-l-sed-p1">
      <memberof>articles_commth</memberof>
      <fileid>art-ct-l-sed-p1</fileid>
    </doc>
    <doc id="art-ct-l-sed-p2">
      <memberof>articles_commth</memberof>
      <fileid>art-ct-l-sed-p2</fileid>
    </doc>
    <doc id="art-ct-l-sed-p3">
      <memberof>articles_commth</memberof>
      <fileid>art-ct-l-sed-p3</fileid>
    </doc>
    <doc id="art-ct-l-awk-p1">
      <memberof>articles_commth</memberof>
      <fileid>art-ct-l-awk-p1</fileid>
    </doc>
    <doc id="art-ct-l-awk-p2">
      <memberof>articles_commth</memberof>
      <fileid>art-ct-l-awk-p2</fileid>
    </doc>
    <doc id="art-ct-l-awk-p3">
      <memberof>articles_commth</memberof>
      <fileid>art-ct-l-awk-p3</fileid>
    </doc>
    <doc id="art-ct-l-posix-p1">
      <memberof>articles_commth</memberof>
      <fileid>art-ct-l-posix-p1</fileid>
    </doc>
    <doc id="art-ct-l-posix-p2">
      <memberof>articles_commth</memberof>
      <fileid>art-ct-l-posix-p2</fileid>
    </doc>
    <doc id="art-ct-l-posix-p3">
      <memberof>articles_commth</memberof>
      <fileid>art-ct-l-posix-p3</fileid>
    </doc>
    <doc id="art-ct-sta-iptables-fw">
      <memberof>articles_commth</memberof>
      <fileid>art-ct-sta-iptables-fw</fileid>
    </doc>
    <doc id="afig-ct-ext3-intro">
      <memberof>articles_commth</memberof>
      <fileid>afig-ct-ext3-intro</fileid>
    </doc>
    <doc id="samba-p1">
      <memberof>articles_commth</memberof>
      <fileid>samba-p1</fileid>
    </doc>
    <doc id="samba-p2">
      <memberof>articles_commth</memberof>
      <fileid>samba-p2</fileid>
    </doc>
    <doc id="samba-p3">
      <memberof>articles_commth</memberof>
      <fileid>samba-p3</fileid>
    </doc>
    <doc id="l-redesign-1">
      <memberof>articles_commth</memberof>
      <fileid>l-redesign-1</fileid>
    </doc>
    <doc id="l-redesign-2">
      <memberof>articles_commth</memberof>
      <fileid>l-redesign-2</fileid>
    </doc>
    <doc id="l-redesign-3">
      <memberof>articles_commth</memberof>
      <fileid>l-redesign-3</fileid>
    </doc>
    <doc id="l-redesign-4">
      <memberof>articles_commth</memberof>
      <fileid>l-redesign-4</fileid>
    </doc>
    <doc id="autotools-practices">
      <memberof>articles_others</memberof>
      <fileid>autotools-practices</fileid>
    </doc>
    <doc id="hardware-stability-p1">
      <memberof>articles_others</memberof>
      <fileid>hardware-stability-p1</fileid>
    </doc>
    <doc id="hardware-stability-p2">
      <memberof>articles_others</memberof>
      <fileid>hardware-stability-p2</fileid>
    </doc>
    <doc id="partitioning-p1">
      <memberof>articles_linux</memberof>
      <fileid>partitioning-p1</fileid>
    </doc>
    <doc id="partitioning-p2">
      <memberof>articles_linux</memberof>
      <fileid>partitioning-p2</fileid>
    </doc>
    <doc id="partition-planning-tips">
      <memberof>articles_linux</memberof>
      <fileid>partition-planning-tips</fileid>
    </doc>
    <doc id="maximum-swappage">
      <memberof>articles_linux</memberof>
      <fileid>maximum-swappage</fileid>
    </doc>
    <doc id="lvm-p1">
      <memberof>articles_linux</memberof>
      <fileid>lvm-p1</fileid>
    </doc>
    <doc id="lvm-p2">
      <memberof>articles_linux</memberof>
      <fileid>lvm-p2</fileid>
    </doc>
    <doc id="software-raid-p1">
      <memberof>articles_linux</memberof>
      <fileid>software-raid-p1</fileid>
    </doc>
    <doc id="software-raid-p2">
      <memberof>articles_linux</memberof>
      <fileid>software-raid-p2</fileid>
    </doc>
    <doc id="linux-kernel-compiling">
      <memberof>articles_linux</memberof>
      <fileid>linux-kernel-compiling</fileid>
    </doc>
    <doc id="art-prompt-magic">
      <memberof>articles_linux</memberof>
      <fileid>art-prompt-magic</fileid>
    </doc>
    <doc id="openssh-key-management-p1">
      <memberof>articles_linux</memberof>
      <fileid>openssh-key-management-p1</fileid>
    </doc>
    <doc id="openssh-key-management-p2">
      <memberof>articles_linux</memberof>
      <fileid>openssh-key-management-p2</fileid>
    </doc>
    <doc id="openssh-key-management-p3">
      <memberof>articles_linux</memberof>
      <fileid>openssh-key-management-p3</fileid>
    </doc>
    <doc id="l-afig-p8">
      <memberof>articles_linux</memberof>
       <fileid>l-afig-p8</fileid>
    </doc>
    <doc id="bugzilla-howto">
      <memberof>other</memberof>
      <fileid>bugzie-howto</fileid>
    </doc>
     <doc id="mysql-howto">
     <memberof>sysadmin_specific</memberof>
     <fileid>mysql-howto</fileid>
    </doc>
    <doc id="postgres-howto">
      <memberof>sysadmin_specific</memberof>
      <fileid>postgres-howto</fileid>
    </doc>
    <doc id="bluetooth-guide">
     <memberof>install_other</memberof>
     <fileid>bt-guide</fileid>
    </doc>
    <doc id="utf-8">
      <memberof>sysadmin_general</memberof>
      <memberof>desktop_config</memberof>
      <fileid>utf-8</fileid>
    </doc>
    <doc id="handbook_index">
      <memberof>install_guides</memberof>
      <fileid>handbook_index</fileid>
    </doc>
    <doc id="2007.0-index">
      <memberof>install_guides</memberof>
      <fileid>2007.0-index</fileid>
    </doc>
    <doc id="gentoo-x86-quickinstall">
      <memberof>install_guides</memberof>
      <fileid>gentoo-x86-quickinstall</fileid>
    </doc>
    <doc id="gentoo-x86-quickinstall+raid">
      <memberof>install_guides</memberof>
      <fileid>gentoo-x86-quickinstall+raid</fileid>
    </doc>
    <doc id="gentoo-sparc-quickinstall">
      <memberof>install_guides</memberof>
      <fileid>gentoo-sparc-quickinstall</fileid>
    </doc>
    <doc id="faq">
      <memberof>faq</memberof>
      <fileid>faq</fileid>
    </doc>
    <doc id="gentoo-alpha-faq">
      <memberof>faq</memberof>
      <fileid>gentoo-alpha-faq</fileid>
    </doc>
        <doc id="amd64-howtos">
      <memberof>project_base</memberof>
      <fileid>amd64-howtos</fileid>
    </doc>
    <doc id="gentoo-ppc-faq">
      <memberof>faq</memberof>
      <fileid>gentoo-ppc-faq</fileid>
    </doc>
    <doc id="gentoo-amd64-faq">
     <memberof>faq</memberof>
     <fileid>gentoo-amd64-faq</fileid>
    </doc>
    <doc id="gentoo-sparc-faq">
      <memberof>faq</memberof>
      <fileid>gentoo-sparc-faq</fileid>
    </doc>
    <doc id="altinstall">
      <memberof>install_other</memberof>
      <fileid>altinstall</fileid>
    </doc>
    <doc id="lvm2">
      <memberof>install_other</memberof>
      <fileid>lvm2</fileid>
    </doc>
    <doc id="gentoo-x86-tipsntricks">
      <memberof>install_other</memberof>
      <fileid>gentoo-x86-tipsntricks</fileid>
    </doc>
    <doc id="new-upgrade-to-gentoo-1.4">
      <memberof>install_other</memberof>
      <memberof>upgrade</memberof>
      <fileid>new-upgrade-to-gentoo-1.4</fileid>
    </doc>
    <doc id="portage-utils">
      <memberof>gentoo_portage</memberof>
      <fileid>portage-utils</fileid>
    </doc>
    <doc id="gentoo-upgrading">
      <memberof>install_other</memberof>
      <memberof>upgrade</memberof>
      <fileid>gentoo-upgrading</fileid>
    </doc>
    <doc id="2.6-migration">
      <memberof>install_other</memberof>
      <memberof>upgrade</memberof>
      <fileid>2.6-migration</fileid>
    </doc>
    <doc id="genkernel">
      <memberof>install_other</memberof>
      <fileid>genkernel</fileid>
    </doc>
    <doc id="portage-intro">
      <memberof>gentoo_portage</memberof>
      <fileid vpart="2" vchap="1">handbook-x86</fileid>
    </doc>
    <doc id="portage-features">
      <memberof>gentoo_portage</memberof>
      <fileid vpart="2" vchap="3">handbook-x86</fileid>
    </doc>
    <doc id="working-with-portage">
      <memberof>gentoo_portage</memberof>
      <fileid vpart="3">handbook-x86</fileid>
    </doc>
    <doc id="use-flags">
      <memberof>gentoo_portage</memberof>
      <fileid vpart="2" vchap="2">handbook-x86</fileid>
    </doc>
    <doc id="gentoolkit">
      <memberof>gentoo_portage</memberof>
      <fileid>gentoolkit</fileid>
    </doc>
    <doc id="environment-variables">
      <memberof>gentoo_configuring</memberof>
      <fileid vpart="2" vchap="5">handbook-x86</fileid>
    </doc>
    <doc id="initscripts">
      <memberof>gentoo_configuring</memberof>
      <fileid vpart="2" vchap="4">handbook-x86</fileid>
    </doc>
    <doc id="gentoo-kernel">
      <memberof>gentoo_choices</memberof>
      <fileid>gentoo-kernel</fileid>
    </doc>
    <doc id="security-handbook-index">
      <memberof>sysadmin_general</memberof>
      <fileid>security-handbook-index</fileid>
    </doc>
    <doc id="prelink-howto">
      <memberof>sysadmin_general</memberof>
      <fileid>prelink-howto</fileid>
    </doc>
    <doc id="ipv6">
      <memberof>sysadmin_general</memberof>
      <fileid>ipv6</fileid>
    </doc>
    <doc id="uml">
      <memberof>sysadmin_general</memberof>
      <fileid>uml</fileid>
    </doc>
    <doc id="diskless-howto">
      <memberof>sysadmin_specific</memberof>
      <fileid>diskless-howto</fileid>
    </doc>
    <doc id="ltsp">
      <memberof>sysadmin_specific</memberof>
      <fileid>ltsp</fileid>
    </doc>
    <doc id="distcc">
      <memberof>sysadmin_specific</memberof>
      <fileid>distcc</fileid>
    </doc>
    <doc id="cross-distcc">
      <memberof>sysadmin_specific</memberof>
      <fileid>cross-distcc</fileid>
    </doc>
    <doc id="devfs-guide">
      <memberof>sysadmin_specific</memberof>
      <fileid>devfs-guide</fileid>
    </doc>
    <doc id="udev-guide">
      <memberof>sysadmin_specific</memberof>
      <fileid>udev-guide</fileid>
    </doc>
    <doc id="printing-howto">
      <memberof>sysadmin_specific</memberof>
      <fileid>printing-howto</fileid>
    </doc>
    <doc id="openafs">
      <memberof>sysadmin_specific</memberof>
      <fileid>openafs</fileid>
    </doc>
    <doc id="virt-mail-howto">
      <memberof>sysadmin_specific</memberof>
      <fileid>virt-mail-howto</fileid>
    </doc>
    <doc id="mailfilter-guide">
      <memberof>sysadmin_specific</memberof>
      <fileid>mailfilter-guide</fileid>
    </doc>
    <doc id="qmail-howto">
      <memberof>sysadmin_specific</memberof>
      <fileid>qmail-howto</fileid>
    </doc>
    <doc id="gentoo-sparc-netboot-howto">
      <memberof>sysadmin_specific</memberof>
      <fileid>gentoo-sparc-netboot-howto</fileid>
    </doc>
    <doc id="gentoo-sparc-obpreference">
      <memberof>sysadmin_specific</memberof>
      <fileid>gentoo-sparc-obpreference</fileid>
    </doc>
    <doc id="quick-samba-howto">
      <memberof>sysadmin_specific</memberof>
      <fileid>quick-samba-howto</fileid>
    </doc>
    <doc id="home-router-howto">
      <memberof>sysadmin_specific</memberof>
      <fileid>home-router-howto</fileid>
    </doc>
    <doc id="gcc-optimization">
      <memberof>sysadmin_specific</memberof>
      <fileid>gcc-optimization</fileid>
    </doc>
    <doc id="gentoo-dev-handbook">
      <memberof>gentoodev</memberof>
      <memberof>project_devrel</memberof>
      <fileid>gentoo-dev-handbook</fileid>
    </doc>
    <doc id="doc-policy">
      <memberof>gentoodev_policies</memberof>
      <memberof>project_gdp</memberof>
      <fileid>doc-policy</fileid>
    </doc>
    <doc id="ebuild-submit">
      <memberof>gentoodev_docs</memberof>
      <fileid>ebuild-submit</fileid>
    </doc>
    <doc id="xml-guide">
      <memberof>gentoodev_docs</memberof>
      <fileid>xml-guide</fileid>
    </doc>
    <doc id="doc-tipsntricks">
      <memberof>gentoodev_docs</memberof>
      <memberof>project_gdp</memberof>
      <fileid>doc-tipsntricks</fileid>
    </doc>
    <doc id="cvs-tutorial">
      <memberof>gentoodev_docs</memberof>
      <fileid>cvs-tutorial</fileid>
    </doc>
    <doc id="about">
      <memberof>other</memberof>
      <fileid>about</fileid>
    </doc>
    <doc id="philosophy">
      <memberof>other</memberof>
      <fileid>philosophy</fileid>
    </doc>
    <doc id="contract">
      <memberof>other</memberof>
      <fileid>contract</fileid>
    </doc>
    <doc id="contact">
      <memberof>other</memberof>
      <fileid>contact</fileid>
    </doc>
    <doc id="gentoo-graphics">
      <memberof>other</memberof>
      <fileid>gentoo-graphics</fileid>
    </doc>
    <doc id="irc">
      <memberof>other</memberof>
      <fileid>irc</fileid>
    </doc>
    <doc id="mailing-lists">
      <memberof>other</memberof>
      <fileid>mailing-lists</fileid>
    </doc>
    <doc id="screenshots">
      <memberof>other</memberof>
      <fileid>screenshots</fileid>
    </doc>
    <doc id="sponsors">
      <memberof>other</memberof>
      <fileid>sponsors</fileid>
    </doc>
    <doc id="howto-obtain-support">
      <memberof>other</memberof>
      <fileid>howto-obtain-support</fileid>
    </doc>
    <doc id="where-to-get">
      <memberof>other</memberof>
      <fileid>where-to-get</fileid>
    </doc>
    <doc id="site">
      <memberof>other</memberof>
      <fileid>site</fileid>
    </doc>
    <doc id="rsync">
      <memberof>other</memberof>
      <fileid>rsync</fileid>
    </doc>
    <doc id="source_mirrors">
      <memberof>other</memberof>
      <fileid>source_mirrors</fileid>
    </doc>
    <doc id="xorg-config">
      <memberof>desktop_install</memberof>
      <fileid>xorg-config</fileid>
    </doc>
    <doc id="nvidia-guide">
      <memberof>desktop_install</memberof>
      <fileid>nvidia-guide</fileid>
    </doc>
    <doc id="ati-faq">
      <memberof>desktop_install</memberof>
      <fileid>ati-faq</fileid>
    </doc>
    <doc id="kde-config">
      <memberof>desktop_install</memberof>
      <fileid>kde-config</fileid>
    </doc>
    <doc id="gnome-config">
      <memberof>desktop_install</memberof>
      <fileid>gnome-config</fileid>
    </doc>
    <doc id="fluxbox-config">
      <memberof>desktop_install</memberof>
      <fileid>fluxbox-config</fileid>
    </doc>
    <doc id="xfce-config">
      <memberof>desktop_install</memberof>
      <fileid>xfce-config</fileid>
    </doc>
    <doc id="vserver-howto">
      <memberof>sysadmin_specific</memberof>
      <fileid>vserver-howto</fileid>
    </doc>
    <doc id="alsa-guide">
      <memberof>desktop_config</memberof>
      <fileid>alsa-guide</fileid>
    </doc>
    <doc id="java">
      <memberof>desktop_config</memberof>
      <memberof>sysadmin_specific</memberof>
      <fileid>java</fileid>
    </doc>
    <doc id="guide-localization">
      <memberof>desktop_config</memberof>
      <memberof>sysadmin_general</memberof>
      <fileid>guide-localization</fileid>
    </doc>
    <doc id="dri-howto">
      <memberof>desktop_config</memberof>
      <fileid>dri-howto</fileid>
    </doc>
    <doc id="power-management-guide">
      <memberof>desktop_config</memberof>
      <fileid>power-management-guide</fileid>
    </doc>
    <doc id="gpm">
      <memberof>desktop_config</memberof>
      <fileid>gpm</fileid>
    </doc>
    <doc id="kde-split-ebuilds">
      <memberof>desktop_install</memberof>
      <fileid>kde-split-ebuilds</fileid>
    </doc>
    <doc id="nano-basics-guide">
      <memberof>desktop_apps</memberof>
      <fileid>nano-basics-guide</fileid>
    </doc>
    <doc id="vi-guide">
      <memberof>desktop_apps</memberof>
      <fileid>vi-guide</fileid>
    </doc>
    <doc id="gnupg-user">
      <memberof>desktop_apps</memberof>
      <fileid>gnupg-user</fileid>
    </doc>
    <doc id="guide-to-mutt">
      <memberof>desktop_apps</memberof>
      <fileid>guide-to-mutt</fileid>
    </doc>
    <doc id="shoutcast-config">
      <memberof>desktop_apps</memberof>
      <fileid>shoutcast-config</fileid>
    </doc>
    <doc id="vdr-guide">
      <memberof>desktop_apps</memberof>
      <fileid>vdr-guide</fileid>
    </doc>
    <doc id="cron-guide">
      <memberof>sysadmin_general</memberof>
      <fileid>cron-guide</fileid>
    </doc>
    <doc id="kernel-upgrade">
      <memberof>sysadmin_general</memberof>
      <memberof>upgrade</memberof>
      <fileid>kernel-upgrade</fileid>
    </doc>
    <doc id="ldap-howto">
      <memberof>sysadmin_specific</memberof>
      <fileid>ldap-howto</fileid> 
    </doc>
    <doc id="new-dev-training">
      <memberof>project_devrel</memberof>
      <fileid>new-dev-training</fileid>
    </doc>
    <doc id="devrel-policy">
      <memberof>gentoodev_policies</memberof>
      <memberof>project_devrel</memberof>
      <fileid>devrel-policy</fileid>
    </doc>
    <doc id="translators-howto">
      <memberof>project_gdp</memberof>
      <fileid>translators-howto</fileid>
    </doc>
    <doc id="hardened-primer">
      <memberof>project_hardened</memberof>
      <fileid>hardened-primer</fileid>
    </doc>
    <doc id="hardened-faq">
      <memberof>project_hardened</memberof>
      <fileid>hardened-faq</fileid>
    </doc>
    <doc id="hardened-xorg">
      <memberof>project_hardened</memberof>
      <fileid>hardened-xorg</fileid>
    </doc>
    <doc id="hardened-pax-quickstart">
      <memberof>project_hardened</memberof>
      <fileid>hardened-pax-quickstart</fileid>
    </doc>
    <doc id="hardened-grsec">
      <memberof>project_hardened</memberof>
      <fileid>hardened-grsec</fileid>
    </doc>
    <doc id="hardened-capabilities">
      <memberof>project_hardened</memberof>
      <fileid>hardened-capabilities</fileid>
    </doc>
    <doc id="hardened-selinux">
      <memberof>project_hardened</memberof>
      <fileid>hardened-selinux</fileid>
    </doc>
    <doc id="hardened-rsbac-overview">
      <memberof>project_hardened</memberof>
      <fileid>hardened-rsbac-overview</fileid>
    </doc>
    <doc id="hardened-rsbac-quickstart">
      <memberof>project_hardened</memberof>
      <fileid>hardened-rsbac-quickstart</fileid>
    </doc>
    <doc id="infra-email">
      <memberof>project_infra</memberof>
      <fileid>infra-email</fileid>
    </doc>
    <doc id="infra-cvsssh">
      <memberof>project_infra</memberof>
      <fileid>infra-cvsssh</fileid>
    </doc>
    <doc id="infra-machines">
      <memberof>project_infra</memberof>
      <fileid>infra-machines</fileid>
    </doc>
    <doc id="infra-servers">
      <memberof>project_infra</memberof>
      <fileid>infra-servers</fileid>
    </doc>
    <doc id="infra-serverstandards">
      <memberof>project_infra</memberof>
      <fileid>infra-serverstandards</fileid>
    </doc>
    <doc id="infra-tenshi">
      <memberof>project_infra</memberof>
      <fileid>infra-tenshi</fileid>
    </doc>
    <doc id="infra-ntp">
      <memberof>project_infra</memberof>
      <fileid>infra-ntp</fileid>
    </doc>
    <doc id="infra-ssh">
      <memberof>project_infra</memberof>
      <fileid>infra-ssh</fileid>
    </doc>
    <doc id="infra-syslog">
      <memberof>project_infra</memberof>
      <fileid>infra-syslog</fileid>
    </doc>
    <doc id="infra-webspace">
      <memberof>project_infra</memberof>
      <fileid>infra-webspace</fileid>
    </doc>
    <doc id="infra-faq">
      <memberof>project_infra</memberof>
      <fileid>infra-faq</fileid>
    </doc>
    <doc id="infra-rsync">
      <memberof>project_infra</memberof>
      <fileid>infra-rsync</fileid>
    </doc>
    <doc id="metastructure-projectxml">
      <memberof>project_metastructure</memberof>
      <fileid>metastructure-projectxml</fileid>
    </doc>
    <doc id="pr-presentation">
      <memberof>project_pr</memberof>
      <fileid>pr-presentation</fileid>
    </doc>
    <doc id="catalyst-faq">
      <memberof>project_releng</memberof>
      <fileid>catalyst-faq</fileid>
    </doc>
    <doc id="installer-design">
      <memberof>project_releng</memberof>
      <fileid>installer-design</fileid>
    </doc>
    <doc id="releng-guidelines">
      <memberof>project_releng</memberof>
      <memberof>gentoodev_policies</memberof>
      <fileid>releng-guidelines</fileid>
    </doc>
    <doc id="profile-update">
      <memberof>project_releng</memberof>
      <fileid>profile-update</fileid>
    </doc>
    <doc id="security-index">
      <memberof>project_security</memberof>
      <fileid>security-index</fileid>
    </doc>
    <doc id="security-policy">
      <memberof>project_security</memberof>
      <memberof>gentoodev_policies</memberof>
      <fileid>security-policy</fileid>
    </doc>
    <doc id="security-coordination">
      <memberof>project_security</memberof>
      <fileid>security-coordination</fileid>
    </doc>
    <doc id="security-recruitment">
      <memberof>project_security</memberof>
      <fileid>security-recruitment</fileid>
    </doc>
    <doc id="security-bugs">
      <memberof>project_security</memberof>
      <fileid>security-bugs</fileid>
    </doc>
    <doc id="forums-mod-guide">
      <memberof>project_forums</memberof>
      <fileid>forums-guide</fileid>
    </doc>
    <doc id="keychain-guide">
      <memberof>desktop_apps</memberof>
      <memberof>sysadmin_specific</memberof>
      <fileid>keychain-guide</fileid>
    </doc>
    <doc id="metadoc-guide">
      <memberof>project_gdp</memberof>
      <fileid>metadoc-guide</fileid>
    </doc>
    <doc id="hpc-howto">
      <memberof>sysadmin_specific</memberof>
      <fileid>hpc-howto</fileid>
    </doc>
    <doc id="gnap-userguide">
      <memberof>project_base</memberof>
      <fileid>gnap-userguide</fileid>
    </doc>
    <doc id="mips-requirements">
      <memberof>install_other</memberof>
      <fileid>mips-requirements</fileid>
    </doc>
    <doc id="grub-error-guide">
      <memberof>install_other</memberof>
      <fileid>grub-error-guide</fileid>
    </doc>
    <doc id="usb-guide">
      <memberof>install_other</memberof>
      <fileid>usb-guide</fileid>
    </doc>
    <doc id="liveusb">
      <memberof>install_other</memberof>
      <fileid>liveusb</fileid>
    </doc>
    <doc id="apache-troubleshooting">
      <memberof>sysadmin_specific</memberof>
      <fileid>apache-troubleshooting</fileid>
    </doc>
    <doc id="apache-upgrading">
      <memberof>sysadmin_specific</memberof>
      <memberof>upgrade</memberof>
      <fileid>apache-upgrading</fileid>
    </doc>
    <doc id="apache-developer">
      <memberof>gentoodev_docs</memberof>
      <fileid>apache-developer</fileid>
    </doc>
    <doc id="sudo-guide">
      <memberof>sysadmin_general</memberof>
      <fileid>sudo-guide</fileid>
    </doc>
    <doc id="freebsd-guide">
      <memberof>install_guides</memberof>
      <memberof>project_base</memberof>
      <fileid>freebsd-guide</fileid>
    </doc>
    <doc id="mips-faq">
      <memberof>faq</memberof>
      <fileid>mips-faq</fileid>
    </doc>
    <doc id="mysql-upgrading">
      <memberof>sysadmin_specific</memberof>
      <memberof>upgrade</memberof>
      <fileid>mysql-upgrading</fileid>
    </doc>
    <doc id="mysql-upgrade-slotted">
      <memberof>sysadmin_specific</memberof>
      <memberof>upgrade</memberof>
      <fileid>mysql-upgrade-slotted</fileid>
    </doc>
    <doc id="gcc-upgrading">
      <memberof>sysadmin_specific</memberof>
      <memberof>upgrade</memberof>
      <fileid>gcc-upgrading</fileid>
    </doc>
    <doc id="change-chost">
      <memberof>sysadmin_specific</memberof>
      <memberof>upgrade</memberof>
      <fileid>change-chost</fileid>
    </doc>
    <doc id="x86-at-faq">
      <memberof>project_base</memberof>
      <fileid>x86-at-faq</fileid>
    </doc>
    <doc id="gnome-upgrade">
      <memberof>desktop_install</memberof>
      <memberof>upgrade</memberof>
      <fileid>gnome-upgrade</fileid>
    </doc>
    <doc id="modular-x-howto">
      <memberof>desktop</memberof>
      <memberof>upgrade</memberof>
      <fileid>modular-x-howto</fileid>
    </doc>
    <doc id="porting-modular-x">
      <memberof>desktop</memberof>
      <memberof>gentoodev_docs</memberof>
      <fileid>porting-modular-x</fileid>
    </doc>
    <doc id="php-upgrade">
      <memberof>sysadmin_specific</memberof>
      <memberof>upgrade</memberof>
      <fileid>php-upgrade</fileid>
    </doc>
    <doc id="jffnms">
      <memberof>sysadmin_specific</memberof>
      <fileid>jffnms</fileid>
    </doc>
    <doc id="vpnc-howto">
      <memberof>sysadmin_specific</memberof>
      <fileid>vpnc-howto</fileid>
    </doc>
    <doc id="conky">
      <memberof>desktop_config</memberof>
      <fileid>conky</fileid>
    </doc>
    <doc id="ldapdns">
      <memberof>sysadmin_specific</memberof>
      <fileid>ldapdns</fileid>
    </doc>
    <doc id="man-guide">
      <memberof>sysadmin_general</memberof>
      <fileid>man-guide</fileid>
    </doc>
    <doc id="info-guide">
      <memberof>sysadmin_general</memberof>
      <fileid>info-guide</fileid>
    </doc>
    <doc id="java-upgrade">
      <memberof>upgrade</memberof>
      <fileid>java-upgrade</fileid>
    </doc>
    <doc id="kernel-config">
      <memberof>sysadmin_general</memberof>
      <fileid>kernel-config</fileid>
    </doc>
    <doc id="zsh">
      <memberof>sysadmin_general</memberof>
      <fileid>zsh</fileid>
    </doc>
    <doc id="qa-autofailure">
      <memberof>gentoodev_docs</memberof>
      <fileid>qa-autofailure</fileid>
    </doc>
    <doc id="qa-automagic">
      <memberof>gentoodev_docs</memberof>
      <fileid>qa-automagic</fileid>
    </doc>
    <doc id="qa-backtraces">
      <memberof>sysadmin_specific</memberof>
      <fileid>qa-backtraces</fileid>
    </doc>
    <doc id="manually-fixing-portage">
      <memberof>gentoo_portage</memberof>
      <fileid>manually-fixing-portage</fileid>
    </doc>
  </docs>
</metadoc>
